{
  "tags": [
    {
      "name": "release",
      "version": "4.3.7.99-202108032349-7395-0415c0c6f",
      "commit": "de11718",
      "upstream": "Stable",
      "lastUpdated": "2021-08-08T21:29:13.751Z"
    },
    {
      "name": "testing",
      "version": "4.4.0-202106140855-7320-2bd5aca3a",
      "commit": "06bce75",
      "upstream": "Unstable",
      "lastUpdated": "2021-08-08T21:31:03.761Z"
    },
    {
      "name": "nightly",
      "version": "",
      "commit": "",
      "upstream": "",
      "lastUpdated": ""
    }
  ],
  "pulls": 753883,
  "stars": 4
}
